plaited/__init__.py
plaited/main.py
plaited/options.py
plaited/plaited.py
plaited-0.0.1.dist-info/LICENSE
plaited-0.0.1.dist-info/METADATA
plaited-0.0.1.dist-info/WHEEL
plaited-0.0.1.dist-info/entry_points.txt
plaited-0.0.1.dist-info/top_level.txt
plaited-0.0.1.dist-info/RECORD
