Metadata-Version: 2.1
Name: plaited
Version: 0.0.1
Summary: Publish reproducible code notebooks using pandoc and jupyter kernels
Home-page: https://github.com/jacobwhall/plaited
Author: Jacob Hall
Author-email: email@jacobhall.net
License: BSD 3-Clause License
Project-URL: Bug Tracker, https://github.com/jacobwhall/plaited/issues
Keywords: pandoc,jupyter,notebook
Classifier: Programming Language :: Python :: 3
License-File: LICENSE
Requires-Dist: panflute
Requires-Dist: ipykernel
Requires-Dist: jupyter-client
Requires-Dist: nbconvert
